rushlib/__init__.py
rushlib/args.py
rushlib/math.py
rushlib/message.py
rushlib/modulelib.py
rushlib/output.py
rushlib/path.py
rushlib/text.py
rushlib/types.py
rushlib/zip.py
rushlib/color/__init__.py
rushlib/color/util.py
rushlib/color/_console/__init__.py
rushlib/file/__init__.py
rushlib/file/json.py
rushlib/file/plist.py
rushlib/func/__init__.py
rushlib/func/injection.py
rushlib/func/wrapper.py
rushlib/system/__init__.py
rushlib/venvs/__init__.py
rushlib/venvs/path.py
rushlib/venvs/version.py
rushlib-0.2.0.dist-info/licenses/LICENSE.txt
scripts/build.py
scripts/install.py
scripts/upload.py
test/color.py
test/venv.py
test/wrap.py
rushlib-0.2.0.dist-info/METADATA
rushlib-0.2.0.dist-info/WHEEL
rushlib-0.2.0.dist-info/top_level.txt
rushlib-0.2.0.dist-info/RECORD
