Metadata-Version: 2.4
Name: rushlib
Version: 0.2.0
Summary: python lib
Author-email: ndrzy <dandan0019@outlook.com>
License: MIT
Project-URL: Homepage, https://github.com/meatdumplings0019/rushlib
Requires-Python: >=3.10
License-File: LICENSE.txt
Requires-Dist: colorama
Dynamic: license-file
